sqlrender.py
sqlrender-1.0.4.dist-info/licenses/LICENSE
sqlrender-1.0.4.dist-info/METADATA
sqlrender-1.0.4.dist-info/WHEEL
sqlrender-1.0.4.dist-info/top_level.txt
sqlrender-1.0.4.dist-info/RECORD
