Metadata-Version: 2.4
Name: sqlrender
Version: 1.0.4
Summary: Simple and fast sql templating engine inspired by the classical library MyBatis.
Author-email: Jiri Kacirek <kacirek.j@gmail.com>
License: Copyright (c) 2024-2025, Jiri Kacirek.
Project-URL: Homepage, https://github.com/kacirekj/sqlrender
Requires-Python: >=3.6
License-File: LICENSE
Requires-Dist: bottle
Dynamic: license-file
